keyrock_model/__init__.py
keyrock_model/model/__init__.py
keyrock_model/model/base_model.py
keyrock_model/model/factory.py
keyrock_model/model/test_model.py
keyrock_model-2024.2.15.1117.dist-info/METADATA
keyrock_model-2024.2.15.1117.dist-info/WHEEL
keyrock_model-2024.2.15.1117.dist-info/top_level.txt
keyrock_model-2024.2.15.1117.dist-info/RECORD
